{"cp":"24320","departement":"24","deptNom":"Dordogne","deptSlug":"24-dordogne","ville":"La Tour-Blanche-Cercles","stats":{"totalStations":2,"totalRupture":2,"tauxRupture":100,"prixMoyen":{"gazole":null,"sp95":2.17,"e10":null,"sp98":2.063,"e85":null,"gplc":null}},"stations":[{"id":24320002,"adresse":"11 rue Passadour","ville":"La Tour-Blanche-Cercles","cp":"24320","departement":"24","lat":45.369,"lon":0.446,"prix":{"gazole":null,"sp95":2.17,"e10":null,"sp98":2.063,"e85":null,"gplc":null},"maj":{"gazole":null,"sp95":"2026-03-25T09:53:40+00:00","e10":null,"sp98":"2026-03-25T09:53:40+00:00","e85":null,"gplc":null},"ruptures":{"temporaire":["Gazole"],"definitive":["E85","GPLc","E10"]},"carburantsDisponibles":["SP95","SP98"],"horaires":"Automate-24-24, Lundi08.00-18.00, Mardi08.00-18.00, Mercredi08.00-18.00, Jeudi08.00-18.00, Vendredi08.00-18.00, Samedi, Dimanche","automate24h":true,"services":["Station de gonflage","Carburant additivé","Lavage manuel","Services réparation / entretien","Vente d'additifs carburants","Automate CB 24/24"]},{"id":24320002,"adresse":"11 rue Passadour","ville":"La Tour-Blanche-Cercles","cp":"24320","departement":"24","lat":45.369,"lon":0.446,"prix":{"gazole":null,"sp95":2.17,"e10":null,"sp98":2.063,"e85":null,"gplc":null},"maj":{"gazole":null,"sp95":"2026-03-25T09:53:40+00:00","e10":null,"sp98":"2026-03-25T09:53:40+00:00","e85":null,"gplc":null},"ruptures":{"temporaire":["Gazole"],"definitive":["E85","GPLc","E10"]},"carburantsDisponibles":["SP95","SP98"],"horaires":"Automate-24-24, Lundi08.00-18.00, Mardi08.00-18.00, Mercredi08.00-18.00, Jeudi08.00-18.00, Vendredi08.00-18.00, Samedi, Dimanche","automate24h":true,"services":["Station de gonflage","Carburant additivé","Lavage manuel","Services réparation / entretien","Vente d'additifs carburants","Automate CB 24/24"]}]}