{"cp":"32340","departement":"32","deptNom":"Gers","deptSlug":"32-gers","ville":"Miradoux","stats":{"totalStations":1,"totalRupture":1,"tauxRupture":100,"prixMoyen":{"gazole":2.38,"sp95":null,"e10":2.07,"sp98":2.22,"e85":null,"gplc":null}},"stations":[{"id":32340001,"adresse":"Place du Foirail","ville":"Miradoux","cp":"32340","departement":"32","lat":43.998,"lon":0.757,"prix":{"gazole":2.38,"sp95":null,"e10":2.07,"sp98":2.22,"e85":null,"gplc":null},"maj":{"gazole":"2026-04-07T13:37:13+00:00","sp95":null,"e10":"2026-04-02T08:52:06+00:00","sp98":"2026-04-07T13:37:13+00:00","e85":null,"gplc":null},"ruptures":{"temporaire":[],"definitive":["SP95","E85","GPLc"]},"carburantsDisponibles":["Gazole","E10","SP98"],"horaires":"","automate24h":false,"services":["DAB (Distributeur automatique de billets)"]}]}