{"cp":"56680","departement":"56","deptNom":"Morbihan","deptSlug":"56-morbihan","ville":"Plouhinec","stats":{"totalStations":1,"totalRupture":1,"tauxRupture":100,"prixMoyen":{"gazole":2.299,"sp95":null,"e10":1.99,"sp98":null,"e85":0.759,"gplc":null}},"stations":[{"id":56680001,"adresse":"Rue du 19 Mars 1962","ville":"Plouhinec","cp":"56680","departement":"56","lat":47.696,"lon":-3.245,"prix":{"gazole":2.299,"sp95":null,"e10":1.99,"sp98":null,"e85":0.759,"gplc":null},"maj":{"gazole":"2026-04-01T12:21:18+00:00","sp95":null,"e10":"2026-04-01T12:21:18+00:00","sp98":null,"e85":"2026-03-26T15:50:26+00:00","gplc":null},"ruptures":{"temporaire":["SP98"],"definitive":["SP95","GPLc"]},"carburantsDisponibles":["Gazole","E85","E10"],"horaires":"Automate-24-24, Lundi09.00-19.00, Mardi09.00-19.00, Mercredi09.00-19.00, Jeudi09.00-19.00, Vendredi09.00-19.00, Samedi09.00-19.00, Dimanche09.00-12.00","automate24h":true,"services":["Toilettes publiques","Laverie","Station de gonflage","Piste poids lourds","Lavage automatique","Lavage manuel","Vente de gaz domestique (Butane, Propane)","Automate CB 24/24"]}]}