{"cp":"71190","departement":"71","deptNom":"Saone-et-Loire","deptSlug":"71-saone-et-loire","ville":"Étang-sur-Arroux","stats":{"totalStations":1,"totalRupture":1,"tauxRupture":100,"prixMoyen":{"gazole":2.499,"sp95":2.09,"e10":null,"sp98":2.185,"e85":null,"gplc":null}},"stations":[{"id":71190003,"adresse":"47 rue Gabriel Bouthiere","ville":"Étang-sur-Arroux","cp":"71190","departement":"71","lat":46.866,"lon":4.19,"prix":{"gazole":2.499,"sp95":2.09,"e10":null,"sp98":2.185,"e85":null,"gplc":null},"maj":{"gazole":"2026-04-03T12:17:29+00:00","sp95":"2026-04-03T12:17:30+00:00","e10":null,"sp98":"2026-04-03T12:17:30+00:00","e85":null,"gplc":null},"ruptures":{"temporaire":[],"definitive":["E85","GPLc","E10"]},"carburantsDisponibles":["Gazole","SP95","SP98"],"horaires":"Automate-24-24, Lundi00.00-00.00, Mardi00.00-00.00, Mercredi00.00-00.00, Jeudi00.00-00.00, Vendredi00.00-00.00, Samedi00.00-00.00, Dimanche00.00-00.00","automate24h":true,"services":["Vente de gaz domestique (Butane, Propane)","Automate CB 24/24"]}]}