{"cp":"72310","departement":"72","deptNom":"Sarthe","deptSlug":"72-sarthe","ville":"Bessé-sur-Braye","stats":{"totalStations":2,"totalRupture":2,"tauxRupture":100,"prixMoyen":{"gazole":2.269,"sp95":1.99,"e10":2.03,"sp98":2.107,"e85":null,"gplc":null}},"stations":[{"id":72310001,"adresse":"LES SABLONNIERES","ville":"Bessé-sur-Braye","cp":"72310","departement":"72","lat":47.842,"lon":0.756,"prix":{"gazole":2.447,"sp95":null,"e10":2.03,"sp98":2.107,"e85":null,"gplc":null},"maj":{"gazole":"2026-04-07T08:23:54+00:00","sp95":null,"e10":"2026-04-03T08:10:58+00:00","sp98":"2026-04-03T08:10:58+00:00","e85":null,"gplc":null},"ruptures":{"temporaire":[],"definitive":["SP95","E85","GPLc"]},"carburantsDisponibles":["Gazole","E10","SP98"],"horaires":"Automate-24-24","automate24h":true,"services":["Laverie","Relais colis","Boutique alimentaire","Boutique non alimentaire","Restauration à emporter","Vente de fioul domestique","Station de gonflage","Location de véhicule","Piste poids lourds","Lavage automatique","Lavage manuel","Vente de gaz domestique (Butane, Propane)","Bornes électriques","Automate CB 24/24","DAB (Distributeur automatique de billets)"]},{"id":72310002,"adresse":"47 rue du bal de braye","ville":"Bessé-sur-Braye","cp":"72310","departement":"72","lat":47.83,"lon":0.75,"prix":{"gazole":2.09,"sp95":1.99,"e10":null,"sp98":null,"e85":null,"gplc":null},"maj":{"gazole":"2026-04-03T10:13:59+00:00","sp95":"2026-04-03T10:13:59+00:00","e10":null,"sp98":null,"e85":null,"gplc":null},"ruptures":{"temporaire":[],"definitive":["E85","GPLc","E10","SP98"]},"carburantsDisponibles":["Gazole","SP95"],"horaires":"Lundi08.00-18.00, Mardi08.00-18.00, Mercredi08.00-18.00, Jeudi08.00-18.00, Vendredi08.00-18.00, Samedi08.30-12.00, Dimanche","automate24h":false,"services":["Station de gonflage","Piste poids lourds","Services réparation / entretien","Vente de gaz domestique (Butane, Propane)","Vente d'additifs carburants"]}]}