{"cp":"94700","departement":"94","deptNom":"Val-de-Marne","deptSlug":"94-val-de-marne","ville":"Maisons-Alfort","stats":{"totalStations":4,"totalRupture":3,"tauxRupture":75,"prixMoyen":{"gazole":2.383,"sp95":null,"e10":2.132,"sp98":2.226,"e85":0.899,"gplc":null}},"stations":[{"id":94700008,"adresse":"135 AV DU GENERAL LECLERC","ville":"Maisons-Alfort","cp":"94700","departement":"94","lat":48.80623,"lon":2.43809,"prix":{"gazole":null,"sp95":null,"e10":null,"sp98":null,"e85":null,"gplc":null},"maj":{"gazole":null,"sp95":null,"e10":null,"sp98":null,"e85":null,"gplc":null},"ruptures":{"temporaire":["E85"],"definitive":[]},"carburantsDisponibles":[],"horaires":"","automate24h":false,"services":["Boutique alimentaire","Carburant additivé","Vente de gaz domestique (Butane, Propane)"]},{"id":94700005,"adresse":"5 Avenue Léon Blum","ville":"Maisons-Alfort","cp":"94700","departement":"94","lat":48.802,"lon":2.436,"prix":{"gazole":2.352,"sp95":null,"e10":1.999,"sp98":2.079,"e85":null,"gplc":null},"maj":{"gazole":"2026-04-07T18:10:00+00:00","sp95":null,"e10":"2026-04-07T18:10:00+00:00","sp98":"2026-04-07T18:10:00+00:00","e85":null,"gplc":null},"ruptures":{"temporaire":[],"definitive":[]},"carburantsDisponibles":["Gazole","E10","SP98"],"horaires":"","automate24h":false,"services":[]},{"id":94700007,"adresse":"99 AVENUE DU GL LECLERC","ville":"Maisons-Alfort","cp":"94700","departement":"94","lat":48.80694774210001,"lon":2.43827166369,"prix":{"gazole":2.399,"sp95":null,"e10":2.199,"sp98":2.299,"e85":0.899,"gplc":null},"maj":{"gazole":"2026-04-03T06:35:00+00:00","sp95":null,"e10":"2026-04-03T06:36:00+00:00","sp98":"2026-04-03T06:36:00+00:00","e85":"2026-04-03T06:35:00+00:00","gplc":null},"ruptures":{"temporaire":[],"definitive":["SP95","GPLc"]},"carburantsDisponibles":["Gazole","E85","E10","SP98"],"horaires":"","automate24h":false,"services":["Boutique alimentaire","Station de gonflage","Carburant additivé","Lavage automatique","Lavage manuel","Vente de gaz domestique (Butane, Propane)"]},{"id":94700007,"adresse":"99 AVENUE DU GL LECLERC","ville":"Maisons-Alfort","cp":"94700","departement":"94","lat":48.80694774210001,"lon":2.43827166369,"prix":{"gazole":2.399,"sp95":null,"e10":2.199,"sp98":2.299,"e85":0.899,"gplc":null},"maj":{"gazole":"2026-04-03T06:35:00+00:00","sp95":null,"e10":"2026-04-03T06:36:00+00:00","sp98":"2026-04-03T06:36:00+00:00","e85":"2026-04-03T06:35:00+00:00","gplc":null},"ruptures":{"temporaire":[],"definitive":["SP95","GPLc"]},"carburantsDisponibles":["Gazole","E85","E10","SP98"],"horaires":"","automate24h":false,"services":["Boutique alimentaire","Station de gonflage","Carburant additivé","Lavage automatique","Lavage manuel","Vente de gaz domestique (Butane, Propane)"]}]}